{
  "assets": [],
  "author": "GlobalShame",
  "post_date": null,
  "post_text": "October 12, 2019 at 9:48 AM#1Hi, I'm wanting to make a macro that, when the showfile is loaded will ask for a password to be entered. If the password is correct the file opens, if it is incorrect it asks again for the password and if the user presses the [X] button it loads a new blank showfile. I know it can be done as i came across it on festival LD's showfile but obviously couldn't open the file to view the macro.Cheers.",
  "replies": 0,
  "thread_id": "64793",
  "title": "Password macro for login.",
  "url": "https://forum.malighting.com/forum/thread/64793-password-macro-for-login/",
  "views": 0
}