{
  "asset_type_category": "no_assets",
  "asset_types": [],
  "assets": [],
  "author": "maizx2003",
  "needs_rescrape": true,
  "post_date": "2025-09-01T16:37:00",
  "post_text": "September 1, 2025 at 4:37\u202fPM#1Hi guysCan i change the fixturetype via macro? Let says i want change fixtures 101 thru 110 fixturetype from A to B? If yes,it's convenient to do this at layout as change Dmx address.",
  "replies": 0,
  "thread_id": "69338",
  "title": "Can macro change selected fixtures fixturetype?",
  "url": "https://forum.malighting.com/forum/thread/69338-can-macro-change-selected-fixtures-fixturetype/",
  "views": 0
}